highlighter/__init__.py
highlighter/__main__.py
highlighter/analysis.py
highlighter/generator.py
vod_highlighter-0.2.0.dist-info/entry_points.txt
vod_highlighter-0.2.0.dist-info/METADATA
vod_highlighter-0.2.0.dist-info/WHEEL
vod_highlighter-0.2.0.dist-info/RECORD
